docker_diff-0.0.10.dist-info/licenses/LICENSE
docker_diff_pkg/__init__.py
docker_diff_pkg/_version.py
docker_diff_pkg/cli.py
docker_diff_pkg/schema.sql
docker_diff-0.0.10.dist-info/METADATA
docker_diff-0.0.10.dist-info/WHEEL
docker_diff-0.0.10.dist-info/entry_points.txt
docker_diff-0.0.10.dist-info/top_level.txt
docker_diff-0.0.10.dist-info/RECORD
