Metadata-Version: 2.4
Name: docker-diff
Version: 0.0.10
Summary: Docker Image Comparison Database Manager
License: This is free and unencumbered software released into the public domain.
Project-URL: Repository, https://github.com/eapolinario/docker-diff
Requires-Python: >=3.10
License-File: LICENSE
Requires-Dist: libsql-client>=0.3
Dynamic: license-file
